aztecglyph/__init__.py
aztecglyph/__main__.py
aztecglyph/core.py
aztecglyph/utils.py
aztecglyph/extensions/__init__.py
aztecglyph/extensions/django/__init__.py
aztecglyph/extensions/django/fields.py
aztecglyph/extensions/peewee/__init__.py
aztecglyph/extensions/peewee/fields.py
aztecglyph-1.0.2.dist-info/LICENSE
aztecglyph-1.0.2.dist-info/METADATA
aztecglyph-1.0.2.dist-info/WHEEL
aztecglyph-1.0.2.dist-info/entry_points.txt
aztecglyph-1.0.2.dist-info/top_level.txt
aztecglyph-1.0.2.dist-info/RECORD
