Metadata-Version: 2.1
Name: aztecglyph
Version: 1.0.2
Summary: Instances of the AztecGlyph class represent 64-bit UUIDs.
Home-page: https://github.com/angelcamelot/aztecglyph
Author: Angel Camelot
Author-email: dupeyron.camelot@gmail.com
Classifier: Development Status :: 3 - Alpha
Classifier: Intended Audience :: Developers
Classifier: License :: OSI Approved :: MIT License
Classifier: Operating System :: OS Independent
Classifier: Programming Language :: Python
Classifier: Programming Language :: Python :: 3
Classifier: Programming Language :: Python :: 3.6
Classifier: Programming Language :: Python :: 3.7
Classifier: Programming Language :: Python :: 3.8
Classifier: Programming Language :: Python :: 3.9
License-File: LICENSE
Provides-Extra: django
Requires-Dist: django (>=3.2) ; extra == 'django'
Provides-Extra: peewee
Requires-Dist: peewee (>=3.14.4) ; extra == 'peewee'
